pukhlya/__init__.py
pukhlya/classbased.py
pukhlya/saform.py
pukhlya-0.4.0.dist-info/LICENSE
pukhlya-0.4.0.dist-info/METADATA
pukhlya-0.4.0.dist-info/WHEEL
pukhlya-0.4.0.dist-info/top_level.txt
pukhlya-0.4.0.dist-info/RECORD
