Metadata-Version: 2.1
Name: pukhlya
Version: 0.4.0
Summary: Pukhlya is AIOHTTP simple and ready-to-go admin for SQLAlchemy models
Home-page: UNKNOWN
Author: Mikhail Kashkin
Author-email: m@xen.ru
License: UNKNOWN
Keywords: admin,aiohttp,sqlalchemy,wtforms
Platform: POSIX
Classifier: Framework :: AsyncIO
Classifier: Development Status :: 4 - Beta
Classifier: License :: OSI Approved :: MIT License
Classifier: Programming Language :: Python :: 3.6
Classifier: Programming Language :: Python :: 3.7
Classifier: Programming Language :: Python :: 3 :: Only
Classifier: Programming Language :: Python :: Implementation :: CPython
Classifier: Programming Language :: Python :: Implementation :: PyPy
Classifier: Topic :: Internet :: WWW/HTTP :: Session
Requires-Dist: aiohttp (==3.6.2)
Requires-Dist: aiohttp-jinja2 (==1.2.0)
Requires-Dist: aiohttp-session (==2.9.0)
Requires-Dist: async-timeout (==3.0.1)
Requires-Dist: attrs (==19.3.0)
Requires-Dist: chardet (==3.0.4)
Requires-Dist: decorator (==4.4.1)
Requires-Dist: idna (==2.8)
Requires-Dist: infinity (==1.4)
Requires-Dist: intervals (==0.8.1)
Requires-Dist: Jinja2 (==2.10.3)
Requires-Dist: MarkupSafe (==1.1.1)
Requires-Dist: multidict (==4.6.1)
Requires-Dist: six (==1.13.0)
Requires-Dist: SQLAlchemy (==1.3.11)
Requires-Dist: SQLAlchemy-Utils (==0.35.0)
Requires-Dist: validators (==0.14.0)
Requires-Dist: WTForms (==2.2.1)
Requires-Dist: WTForms-Components (==0.10.4)
Requires-Dist: yarl (==1.3.0)
